{
	"tncHeader": {
		"accessibility id": "tandc_summary_label"
	},
	"screenTitle": {
		"accessibility id": "lending.navigation.bar_title_accessibility_id"
	},
	"tncContent": {
		"accessibility id": "tandc_webView"
	},
	"tncAccept": {
		"accessibility id": "tandc_accept_button"
	},
	"tncReject": {
		"accessibility id": "tandc_reject_button"
	},
	"processingInfo": {
		"accessibility id": "tandc_reject_button"
	},
	"inProgress": {
		"accessibility id": "tandc_reject_button"
	},
	"clickHere": {
		"xpath": "//XCUIElementTypeStaticText[@name=\"here\"]"
	}
}
